{
  "id": "798a759d-5306-4a13-bb4d-59f7de751a24",
  "prevId": "00000000-0000-0000-0000-000000000000",
  "version": "7",
  "dialect": "postgresql",
  "tables": {
    "public.bnpl_account": {
      "name": "bnpl_account",
      "schema": "",
      "columns": {
        "id": {
          "name": "id",
          "type": "varchar(36)",
          "primaryKey": true,
          "notNull": true
        },
        "user_id": {
          "name": "user_id",
          "type": "varchar(64)",
          "primaryKey": false,
          "notNull": true
        },
        "payment_profile_id": {
          "name": "payment_profile_id",
          "type": "varchar(36)",
          "primaryKey": false,
          "notNull": true
        },
        "credit_limit": {
          "name": "credit_limit",
          "type": "bigint",
          "primaryKey": false,
          "notNull": true
        },
        "approved_limit": {
          "name": "approved_limit",
          "type": "bigint",
          "primaryKey": false,
          "notNull": true
        },
        "status": {
          "name": "status",
          "type": "bnpl_account_status",
          "typeSchema": "public",
          "primaryKey": false,
          "notNull": true,
          "default": "'ACTIVE'"
        },
        "created_at": {
          "name": "created_at",
          "type": "timestamp with time zone",
          "primaryKey": false,
          "notNull": true,
          "default": "now()"
        },
        "updated_at": {
          "name": "updated_at",
          "type": "timestamp with time zone",
          "primaryKey": false,
          "notNull": true,
          "default": "now()"
        }
      },
      "indexes": {
        "idx_bnpl_account_user_unique": {
          "name": "idx_bnpl_account_user_unique",
          "columns": [
            {
              "expression": "user_id",
              "isExpression": false,
              "asc": true,
              "nulls": "last"
            }
          ],
          "isUnique": true,
          "concurrently": false,
          "method": "btree",
          "with": {}
        }
      },
      "foreignKeys": {
        "bnpl_account_payment_profile_id_payment_profiles_id_fk": {
          "name": "bnpl_account_payment_profile_id_payment_profiles_id_fk",
          "tableFrom": "bnpl_account",
          "tableTo": "payment_profiles",
          "columnsFrom": [
            "payment_profile_id"
          ],
          "columnsTo": [
            "id"
          ],
          "onDelete": "no action",
          "onUpdate": "no action"
        }
      },
      "compositePrimaryKeys": {},
      "uniqueConstraints": {},
      "policies": {},
      "checkConstraints": {},
      "isRLSEnabled": false
    },
    "public.bnpl_collection_events": {
      "name": "bnpl_collection_events",
      "schema": "",
      "columns": {
        "id": {
          "name": "id",
          "type": "varchar(26)",
          "primaryKey": true,
          "notNull": true
        },
        "invoice_id": {
          "name": "invoice_id",
          "type": "varchar(26)",
          "primaryKey": false,
          "notNull": true
        },
        "invoice_item_id": {
          "name": "invoice_item_id",
          "type": "varchar(26)",
          "primaryKey": false,
          "notNull": false
        },
        "event_type": {
          "name": "event_type",
          "type": "varchar(50)",
          "primaryKey": false,
          "notNull": true
        },
        "status": {
          "name": "status",
          "type": "varchar(50)",
          "primaryKey": false,
          "notNull": true
        },
        "payment_event_id": {
          "name": "payment_event_id",
          "type": "varchar(26)",
          "primaryKey": false,
          "notNull": false
        },
        "error_message": {
          "name": "error_message",
          "type": "text",
          "primaryKey": false,
          "notNull": false
        },
        "metadata": {
          "name": "metadata",
          "type": "text",
          "primaryKey": false,
          "notNull": false
        },
        "actor": {
          "name": "actor",
          "type": "varchar(255)",
          "primaryKey": false,
          "notNull": true,
          "default": "'SCHEDULER'"
        },
        "created_at": {
          "name": "created_at",
          "type": "timestamp with time zone",
          "primaryKey": false,
          "notNull": true,
          "default": "now()"
        }
      },
      "indexes": {},
      "foreignKeys": {
        "bnpl_collection_events_invoice_id_bnpl_invoices_id_fk": {
          "name": "bnpl_collection_events_invoice_id_bnpl_invoices_id_fk",
          "tableFrom": "bnpl_collection_events",
          "tableTo": "bnpl_invoices",
          "columnsFrom": [
            "invoice_id"
          ],
          "columnsTo": [
            "id"
          ],
          "onDelete": "no action",
          "onUpdate": "no action"
        },
        "bnpl_collection_events_invoice_item_id_bnpl_invoice_items_id_fk": {
          "name": "bnpl_collection_events_invoice_item_id_bnpl_invoice_items_id_fk",
          "tableFrom": "bnpl_collection_events",
          "tableTo": "bnpl_invoice_items",
          "columnsFrom": [
            "invoice_item_id"
          ],
          "columnsTo": [
            "id"
          ],
          "onDelete": "no action",
          "onUpdate": "no action"
        }
      },
      "compositePrimaryKeys": {},
      "uniqueConstraints": {},
      "policies": {},
      "checkConstraints": {},
      "isRLSEnabled": false
    },
    "public.bnpl_events": {
      "name": "bnpl_events",
      "schema": "",
      "columns": {
        "id": {
          "name": "id",
          "type": "varchar(36)",
          "primaryKey": true,
          "notNull": true
        },
        "bnpl_account_id": {
          "name": "bnpl_account_id",
          "type": "varchar(36)",
          "primaryKey": false,
          "notNull": true
        },
        "payment_session_id": {
          "name": "payment_session_id",
          "type": "varchar(36)",
          "primaryKey": false,
          "notNull": true
        },
        "transaction_type": {
          "name": "transaction_type",
          "type": "text",
          "primaryKey": false,
          "notNull": true
        },
        "status": {
          "name": "status",
          "type": "transaction_status",
          "typeSchema": "public",
          "primaryKey": false,
          "notNull": true
        },
        "amount": {
          "name": "amount",
          "type": "bigint",
          "primaryKey": false,
          "notNull": true
        },
        "created_at": {
          "name": "created_at",
          "type": "timestamp with time zone",
          "primaryKey": false,
          "notNull": true,
          "default": "now()"
        }
      },
      "indexes": {},
      "foreignKeys": {
        "bnpl_events_bnpl_account_id_bnpl_account_id_fk": {
          "name": "bnpl_events_bnpl_account_id_bnpl_account_id_fk",
          "tableFrom": "bnpl_events",
          "tableTo": "bnpl_account",
          "columnsFrom": [
            "bnpl_account_id"
          ],
          "columnsTo": [
            "id"
          ],
          "onDelete": "no action",
          "onUpdate": "no action"
        }
      },
      "compositePrimaryKeys": {},
      "uniqueConstraints": {},
      "policies": {},
      "checkConstraints": {},
      "isRLSEnabled": false
    },
    "public.bnpl_invoice_items": {
      "name": "bnpl_invoice_items",
      "schema": "",
      "columns": {
        "id": {
          "name": "id",
          "type": "varchar(36)",
          "primaryKey": true,
          "notNull": true
        },
        "invoice_id": {
          "name": "invoice_id",
          "type": "varchar(36)",
          "primaryKey": false,
          "notNull": true
        },
        "bnpl_event_id": {
          "name": "bnpl_event_id",
          "type": "varchar(36)",
          "primaryKey": false,
          "notNull": true
        },
        "amount": {
          "name": "amount",
          "type": "bigint",
          "primaryKey": false,
          "notNull": true
        },
        "transaction_date": {
          "name": "transaction_date",
          "type": "timestamp with time zone",
          "primaryKey": false,
          "notNull": true
        },
        "created_at": {
          "name": "created_at",
          "type": "timestamp with time zone",
          "primaryKey": false,
          "notNull": true,
          "default": "now()"
        }
      },
      "indexes": {},
      "foreignKeys": {
        "bnpl_invoice_items_invoice_id_bnpl_invoices_id_fk": {
          "name": "bnpl_invoice_items_invoice_id_bnpl_invoices_id_fk",
          "tableFrom": "bnpl_invoice_items",
          "tableTo": "bnpl_invoices",
          "columnsFrom": [
            "invoice_id"
          ],
          "columnsTo": [
            "id"
          ],
          "onDelete": "no action",
          "onUpdate": "no action"
        },
        "bnpl_invoice_items_bnpl_event_id_bnpl_events_id_fk": {
          "name": "bnpl_invoice_items_bnpl_event_id_bnpl_events_id_fk",
          "tableFrom": "bnpl_invoice_items",
          "tableTo": "bnpl_events",
          "columnsFrom": [
            "bnpl_event_id"
          ],
          "columnsTo": [
            "id"
          ],
          "onDelete": "no action",
          "onUpdate": "no action"
        }
      },
      "compositePrimaryKeys": {},
      "uniqueConstraints": {},
      "policies": {},
      "checkConstraints": {},
      "isRLSEnabled": false
    },
    "public.bnpl_invoices": {
      "name": "bnpl_invoices",
      "schema": "",
      "columns": {
        "id": {
          "name": "id",
          "type": "varchar(36)",
          "primaryKey": true,
          "notNull": true
        },
        "bnpl_account_id": {
          "name": "bnpl_account_id",
          "type": "varchar(36)",
          "primaryKey": false,
          "notNull": true
        },
        "invoice_number": {
          "name": "invoice_number",
          "type": "varchar(50)",
          "primaryKey": false,
          "notNull": true
        },
        "total_amount": {
          "name": "total_amount",
          "type": "bigint",
          "primaryKey": false,
          "notNull": true,
          "default": 0
        },
        "due_date": {
          "name": "due_date",
          "type": "timestamp with time zone",
          "primaryKey": false,
          "notNull": true
        },
        "status": {
          "name": "status",
          "type": "text",
          "primaryKey": false,
          "notNull": true,
          "default": "'PENDING'"
        },
        "pg_transaction_id": {
          "name": "pg_transaction_id",
          "type": "varchar(255)",
          "primaryKey": false,
          "notNull": false
        },
        "period_start": {
          "name": "period_start",
          "type": "timestamp with time zone",
          "primaryKey": false,
          "notNull": true
        },
        "period_end": {
          "name": "period_end",
          "type": "timestamp with time zone",
          "primaryKey": false,
          "notNull": true
        },
        "created_at": {
          "name": "created_at",
          "type": "timestamp with time zone",
          "primaryKey": false,
          "notNull": true,
          "default": "now()"
        },
        "updated_at": {
          "name": "updated_at",
          "type": "timestamp with time zone",
          "primaryKey": false,
          "notNull": true,
          "default": "now()"
        }
      },
      "indexes": {},
      "foreignKeys": {
        "bnpl_invoices_bnpl_account_id_bnpl_account_id_fk": {
          "name": "bnpl_invoices_bnpl_account_id_bnpl_account_id_fk",
          "tableFrom": "bnpl_invoices",
          "tableTo": "bnpl_account",
          "columnsFrom": [
            "bnpl_account_id"
          ],
          "columnsTo": [
            "id"
          ],
          "onDelete": "no action",
          "onUpdate": "no action"
        }
      },
      "compositePrimaryKeys": {},
      "uniqueConstraints": {},
      "policies": {},
      "checkConstraints": {},
      "isRLSEnabled": false
    },
    "public.checkout_sessions": {
      "name": "checkout_sessions",
      "schema": "",
      "columns": {
        "id": {
          "name": "id",
          "type": "varchar(30)",
          "primaryKey": true,
          "notNull": true
        },
        "intent_id": {
          "name": "intent_id",
          "type": "varchar(30)",
          "primaryKey": false,
          "notNull": true
        },
        "redirect_url": {
          "name": "redirect_url",
          "type": "text",
          "primaryKey": false,
          "notNull": true
        },
        "return_url": {
          "name": "return_url",
          "type": "text",
          "primaryKey": false,
          "notNull": true
        },
        "cancel_url": {
          "name": "cancel_url",
          "type": "text",
          "primaryKey": false,
          "notNull": true
        },
        "status": {
          "name": "status",
          "type": "varchar(24)",
          "primaryKey": false,
          "notNull": true,
          "default": "'PENDING'"
        },
        "metadata": {
          "name": "metadata",
          "type": "text",
          "primaryKey": false,
          "notNull": false,
          "default": null
        },
        "expires_at": {
          "name": "expires_at",
          "type": "timestamp with time zone",
          "primaryKey": false,
          "notNull": true
        },
        "created_at": {
          "name": "created_at",
          "type": "timestamp with time zone",
          "primaryKey": false,
          "notNull": true,
          "default": "now()"
        }
      },
      "indexes": {
        "idx_checkout_sessions_intent_id": {
          "name": "idx_checkout_sessions_intent_id",
          "columns": [
            {
              "expression": "intent_id",
              "isExpression": false,
              "asc": true,
              "nulls": "last"
            }
          ],
          "isUnique": false,
          "concurrently": false,
          "method": "btree",
          "with": {}
        },
        "idx_checkout_sessions_status": {
          "name": "idx_checkout_sessions_status",
          "columns": [
            {
              "expression": "status",
              "isExpression": false,
              "asc": true,
              "nulls": "last"
            }
          ],
          "isUnique": false,
          "concurrently": false,
          "method": "btree",
          "with": {}
        },
        "idx_checkout_sessions_created_at": {
          "name": "idx_checkout_sessions_created_at",
          "columns": [
            {
              "expression": "created_at",
              "isExpression": false,
              "asc": true,
              "nulls": "last"
            }
          ],
          "isUnique": false,
          "concurrently": false,
          "method": "btree",
          "with": {}
        },
        "idx_checkout_sessions_expires_at": {
          "name": "idx_checkout_sessions_expires_at",
          "columns": [
            {
              "expression": "expires_at",
              "isExpression": false,
              "asc": true,
              "nulls": "last"
            }
          ],
          "isUnique": false,
          "concurrently": false,
          "method": "btree",
          "with": {}
        }
      },
      "foreignKeys": {
        "checkout_sessions_intent_id_payment_intents_id_fk": {
          "name": "checkout_sessions_intent_id_payment_intents_id_fk",
          "tableFrom": "checkout_sessions",
          "tableTo": "payment_intents",
          "columnsFrom": [
            "intent_id"
          ],
          "columnsTo": [
            "id"
          ],
          "onDelete": "cascade",
          "onUpdate": "no action"
        }
      },
      "compositePrimaryKeys": {},
      "uniqueConstraints": {},
      "policies": {},
      "checkConstraints": {},
      "isRLSEnabled": false
    },
    "public.consents": {
      "name": "consents",
      "schema": "",
      "columns": {
        "id": {
          "name": "id",
          "type": "varchar(36)",
          "primaryKey": true,
          "notNull": true
        },
        "user_id": {
          "name": "user_id",
          "type": "varchar(64)",
          "primaryKey": false,
          "notNull": true
        },
        "cms_batch_profile_id": {
          "name": "cms_batch_profile_id",
          "type": "varchar(36)",
          "primaryKey": false,
          "notNull": true
        },
        "agreement_key": {
          "name": "agreement_key",
          "type": "varchar(36)",
          "primaryKey": false,
          "notNull": false
        },
        "agreement_kind": {
          "name": "agreement_kind",
          "type": "varchar(8)",
          "primaryKey": false,
          "notNull": false
        },
        "status": {
          "name": "status",
          "type": "varchar(16)",
          "primaryKey": false,
          "notNull": true
        },
        "submitted_at": {
          "name": "submitted_at",
          "type": "timestamp with time zone",
          "primaryKey": false,
          "notNull": false
        },
        "reviewed_at": {
          "name": "reviewed_at",
          "type": "timestamp with time zone",
          "primaryKey": false,
          "notNull": false
        },
        "metadata": {
          "name": "metadata",
          "type": "jsonb",
          "primaryKey": false,
          "notNull": false
        },
        "created_at": {
          "name": "created_at",
          "type": "timestamp with time zone",
          "primaryKey": false,
          "notNull": true,
          "default": "now()"
        }
      },
      "indexes": {
        "idx_consents_payment_profile": {
          "name": "idx_consents_payment_profile",
          "columns": [
            {
              "expression": "cms_batch_profile_id",
              "isExpression": false,
              "asc": true,
              "nulls": "last"
            }
          ],
          "isUnique": false,
          "concurrently": false,
          "method": "btree",
          "with": {}
        },
        "idx_consents_status": {
          "name": "idx_consents_status",
          "columns": [
            {
              "expression": "status",
              "isExpression": false,
              "asc": true,
              "nulls": "last"
            }
          ],
          "isUnique": false,
          "concurrently": false,
          "method": "btree",
          "with": {}
        }
      },
      "foreignKeys": {
        "consents_cms_batch_profile_id_cms_batch_profiles_id_fk": {
          "name": "consents_cms_batch_profile_id_cms_batch_profiles_id_fk",
          "tableFrom": "consents",
          "tableTo": "cms_batch_profiles",
          "columnsFrom": [
            "cms_batch_profile_id"
          ],
          "columnsTo": [
            "id"
          ],
          "onDelete": "no action",
          "onUpdate": "no action"
        }
      },
      "compositePrimaryKeys": {},
      "uniqueConstraints": {},
      "policies": {},
      "checkConstraints": {},
      "isRLSEnabled": false
    },
    "public.cms_batch_profiles": {
      "name": "cms_batch_profiles",
      "schema": "",
      "columns": {
        "id": {
          "name": "id",
          "type": "varchar(36)",
          "primaryKey": true,
          "notNull": true
        },
        "member_id": {
          "name": "member_id",
          "type": "varchar(20)",
          "primaryKey": false,
          "notNull": true
        },
        "cms_status": {
          "name": "cms_status",
          "type": "varchar(16)",
          "primaryKey": false,
          "notNull": true
        },
        "payment_company": {
          "name": "payment_company",
          "type": "varchar(3)",
          "primaryKey": false,
          "notNull": false
        },
        "payer_name": {
          "name": "payer_name",
          "type": "varchar(64)",
          "primaryKey": false,
          "notNull": false
        },
        "phone_mask": {
          "name": "phone_mask",
          "type": "varchar(20)",
          "primaryKey": false,
          "notNull": false
        },
        "billing_day": {
          "name": "billing_day",
          "type": "integer",
          "primaryKey": false,
          "notNull": false
        },
        "created_at": {
          "name": "created_at",
          "type": "timestamp with time zone",
          "primaryKey": false,
          "notNull": true,
          "default": "now()"
        },
        "updated_at": {
          "name": "updated_at",
          "type": "timestamp with time zone",
          "primaryKey": false,
          "notNull": true,
          "default": "now()"
        }
      },
      "indexes": {},
      "foreignKeys": {
        "cms_batch_profiles_id_payment_profiles_id_fk": {
          "name": "cms_batch_profiles_id_payment_profiles_id_fk",
          "tableFrom": "cms_batch_profiles",
          "tableTo": "payment_profiles",
          "columnsFrom": [
            "id"
          ],
          "columnsTo": [
            "id"
          ],
          "onDelete": "cascade",
          "onUpdate": "no action"
        }
      },
      "compositePrimaryKeys": {},
      "uniqueConstraints": {
        "cms_batch_profiles_member_id_unique": {
          "name": "cms_batch_profiles_member_id_unique",
          "nullsNotDistinct": false,
          "columns": [
            "member_id"
          ]
        }
      },
      "policies": {},
      "checkConstraints": {},
      "isRLSEnabled": false
    },
    "public.cms_card_profiles": {
      "name": "cms_card_profiles",
      "schema": "",
      "columns": {
        "id": {
          "name": "id",
          "type": "varchar(36)",
          "primaryKey": true,
          "notNull": true
        },
        "member_id": {
          "name": "member_id",
          "type": "varchar(20)",
          "primaryKey": false,
          "notNull": true
        },
        "cms_status": {
          "name": "cms_status",
          "type": "varchar(16)",
          "primaryKey": false,
          "notNull": true
        },
        "payment_company": {
          "name": "payment_company",
          "type": "varchar(3)",
          "primaryKey": false,
          "notNull": false
        },
        "card_last4": {
          "name": "card_last4",
          "type": "varchar(4)",
          "primaryKey": false,
          "notNull": false
        },
        "card_brand": {
          "name": "card_brand",
          "type": "varchar(32)",
          "primaryKey": false,
          "notNull": false
        },
        "payer_name": {
          "name": "payer_name",
          "type": "varchar(64)",
          "primaryKey": false,
          "notNull": false
        },
        "phone_mask": {
          "name": "phone_mask",
          "type": "varchar(20)",
          "primaryKey": false,
          "notNull": false
        },
        "created_at": {
          "name": "created_at",
          "type": "timestamp with time zone",
          "primaryKey": false,
          "notNull": true,
          "default": "now()"
        },
        "updated_at": {
          "name": "updated_at",
          "type": "timestamp with time zone",
          "primaryKey": false,
          "notNull": true,
          "default": "now()"
        }
      },
      "indexes": {
        "uq_cms_card_member": {
          "name": "uq_cms_card_member",
          "columns": [
            {
              "expression": "member_id",
              "isExpression": false,
              "asc": true,
              "nulls": "last"
            }
          ],
          "isUnique": true,
          "concurrently": false,
          "method": "btree",
          "with": {}
        },
        "idx_cms_card_status": {
          "name": "idx_cms_card_status",
          "columns": [
            {
              "expression": "cms_status",
              "isExpression": false,
              "asc": true,
              "nulls": "last"
            }
          ],
          "isUnique": false,
          "concurrently": false,
          "method": "btree",
          "with": {}
        }
      },
      "foreignKeys": {
        "cms_card_profiles_id_payment_profiles_id_fk": {
          "name": "cms_card_profiles_id_payment_profiles_id_fk",
          "tableFrom": "cms_card_profiles",
          "tableTo": "payment_profiles",
          "columnsFrom": [
            "id"
          ],
          "columnsTo": [
            "id"
          ],
          "onDelete": "cascade",
          "onUpdate": "no action"
        }
      },
      "compositePrimaryKeys": {},
      "uniqueConstraints": {
        "cms_card_profiles_member_id_unique": {
          "name": "cms_card_profiles_member_id_unique",
          "nullsNotDistinct": false,
          "columns": [
            "member_id"
          ]
        }
      },
      "policies": {},
      "checkConstraints": {},
      "isRLSEnabled": false
    },
    "public.idempotency_keys": {
      "name": "idempotency_keys",
      "schema": "",
      "columns": {
        "id": {
          "name": "id",
          "type": "varchar(255)",
          "primaryKey": true,
          "notNull": true
        },
        "user_id": {
          "name": "user_id",
          "type": "varchar(64)",
          "primaryKey": false,
          "notNull": true
        },
        "request_path": {
          "name": "request_path",
          "type": "varchar(255)",
          "primaryKey": false,
          "notNull": true
        },
        "request_hash": {
          "name": "request_hash",
          "type": "varchar(64)",
          "primaryKey": false,
          "notNull": true
        },
        "response_code": {
          "name": "response_code",
          "type": "integer",
          "primaryKey": false,
          "notNull": false
        },
        "response_body": {
          "name": "response_body",
          "type": "text",
          "primaryKey": false,
          "notNull": false
        },
        "status": {
          "name": "status",
          "type": "text",
          "primaryKey": false,
          "notNull": true
        },
        "created_at": {
          "name": "created_at",
          "type": "timestamp with time zone",
          "primaryKey": false,
          "notNull": true,
          "default": "now()"
        },
        "expires_at": {
          "name": "expires_at",
          "type": "timestamp with time zone",
          "primaryKey": false,
          "notNull": true
        }
      },
      "indexes": {
        "idx_idempotency_keys_user_id": {
          "name": "idx_idempotency_keys_user_id",
          "columns": [
            {
              "expression": "user_id",
              "isExpression": false,
              "asc": true,
              "nulls": "last"
            }
          ],
          "isUnique": false,
          "concurrently": false,
          "method": "btree",
          "with": {}
        },
        "idx_idempotency_keys_expires_at": {
          "name": "idx_idempotency_keys_expires_at",
          "columns": [
            {
              "expression": "expires_at",
              "isExpression": false,
              "asc": true,
              "nulls": "last"
            }
          ],
          "isUnique": false,
          "concurrently": false,
          "method": "btree",
          "with": {}
        },
        "idx_idempotency_keys_status": {
          "name": "idx_idempotency_keys_status",
          "columns": [
            {
              "expression": "status",
              "isExpression": false,
              "asc": true,
              "nulls": "last"
            }
          ],
          "isUnique": false,
          "concurrently": false,
          "method": "btree",
          "with": {}
        },
        "idx_idempotency_keys_user_status": {
          "name": "idx_idempotency_keys_user_status",
          "columns": [
            {
              "expression": "user_id",
              "isExpression": false,
              "asc": true,
              "nulls": "last"
            },
            {
              "expression": "status",
              "isExpression": false,
              "asc": true,
              "nulls": "last"
            }
          ],
          "isUnique": false,
          "concurrently": false,
          "method": "btree",
          "with": {}
        }
      },
      "foreignKeys": {},
      "compositePrimaryKeys": {},
      "uniqueConstraints": {},
      "policies": {},
      "checkConstraints": {},
      "isRLSEnabled": false
    },
    "public.overdue_accounts": {
      "name": "overdue_accounts",
      "schema": "",
      "columns": {
        "id": {
          "name": "id",
          "type": "varchar(26)",
          "primaryKey": true,
          "notNull": true
        },
        "user_id": {
          "name": "user_id",
          "type": "varchar(64)",
          "primaryKey": false,
          "notNull": true
        },
        "overdue_count": {
          "name": "overdue_count",
          "type": "integer",
          "primaryKey": false,
          "notNull": true,
          "default": 1
        },
        "last_failed_at": {
          "name": "last_failed_at",
          "type": "timestamp with time zone",
          "primaryKey": false,
          "notNull": true,
          "default": "now()"
        },
        "status": {
          "name": "status",
          "type": "varchar(20)",
          "primaryKey": false,
          "notNull": true,
          "default": "'ACTIVE'"
        }
      },
      "indexes": {},
      "foreignKeys": {},
      "compositePrimaryKeys": {},
      "uniqueConstraints": {},
      "policies": {},
      "checkConstraints": {},
      "isRLSEnabled": false
    },
    "public.partners": {
      "name": "partners",
      "schema": "",
      "columns": {
        "id": {
          "name": "id",
          "type": "serial",
          "primaryKey": true,
          "notNull": true
        },
        "mall_id": {
          "name": "mall_id",
          "type": "varchar(36)",
          "primaryKey": false,
          "notNull": true
        },
        "member_id": {
          "name": "member_id",
          "type": "varchar(36)",
          "primaryKey": false,
          "notNull": true
        },
        "name": {
          "name": "name",
          "type": "varchar(100)",
          "primaryKey": false,
          "notNull": true
        },
        "referral_code": {
          "name": "referral_code",
          "type": "varchar(50)",
          "primaryKey": false,
          "notNull": true
        },
        "created_at": {
          "name": "created_at",
          "type": "timestamp with time zone",
          "primaryKey": false,
          "notNull": true,
          "default": "now()"
        }
      },
      "indexes": {
        "idx_partners_mall": {
          "name": "idx_partners_mall",
          "columns": [
            {
              "expression": "mall_id",
              "isExpression": false,
              "asc": true,
              "nulls": "last"
            }
          ],
          "isUnique": false,
          "concurrently": false,
          "method": "btree",
          "with": {}
        },
        "idx_partners_member": {
          "name": "idx_partners_member",
          "columns": [
            {
              "expression": "member_id",
              "isExpression": false,
              "asc": true,
              "nulls": "last"
            }
          ],
          "isUnique": false,
          "concurrently": false,
          "method": "btree",
          "with": {}
        },
        "idx_partners_referral_code": {
          "name": "idx_partners_referral_code",
          "columns": [
            {
              "expression": "referral_code",
              "isExpression": false,
              "asc": true,
              "nulls": "last"
            }
          ],
          "isUnique": true,
          "concurrently": false,
          "method": "btree",
          "with": {}
        }
      },
      "foreignKeys": {},
      "compositePrimaryKeys": {},
      "uniqueConstraints": {},
      "policies": {},
      "checkConstraints": {},
      "isRLSEnabled": false
    },
    "public.payment_attempts": {
      "name": "payment_attempts",
      "schema": "",
      "columns": {
        "id": {
          "name": "id",
          "type": "varchar(36)",
          "primaryKey": true,
          "notNull": true
        },
        "intent_id": {
          "name": "intent_id",
          "type": "varchar(36)",
          "primaryKey": false,
          "notNull": true
        },
        "profile_id": {
          "name": "profile_id",
          "type": "varchar(36)",
          "primaryKey": false,
          "notNull": false
        },
        "instrument_type": {
          "name": "instrument_type",
          "type": "varchar(16)",
          "primaryKey": false,
          "notNull": true,
          "default": "'PROFILE'"
        },
        "provider": {
          "name": "provider",
          "type": "payment_provider",
          "typeSchema": "public",
          "primaryKey": false,
          "notNull": true
        },
        "amount": {
          "name": "amount",
          "type": "bigint",
          "primaryKey": false,
          "notNull": true
        },
        "status": {
          "name": "status",
          "type": "transaction_status",
          "typeSchema": "public",
          "primaryKey": false,
          "notNull": true
        },
        "actor": {
          "name": "actor",
          "type": "text",
          "primaryKey": false,
          "notNull": true,
          "default": "'USER'"
        },
        "event_context": {
          "name": "event_context",
          "type": "jsonb",
          "primaryKey": false,
          "notNull": false
        },
        "created_at": {
          "name": "created_at",
          "type": "timestamp with time zone",
          "primaryKey": false,
          "notNull": true,
          "default": "now()"
        },
        "updated_at": {
          "name": "updated_at",
          "type": "timestamp with time zone",
          "primaryKey": false,
          "notNull": true,
          "default": "now()"
        },
        "error_message": {
          "name": "error_message",
          "type": "text",
          "primaryKey": false,
          "notNull": false
        },
        "transaction_id": {
          "name": "transaction_id",
          "type": "varchar(255)",
          "primaryKey": false,
          "notNull": false
        },
        "approval_number": {
          "name": "approval_number",
          "type": "varchar(255)",
          "primaryKey": false,
          "notNull": false
        }
      },
      "indexes": {
        "idx_payment_attempts_intent_created": {
          "name": "idx_payment_attempts_intent_created",
          "columns": [
            {
              "expression": "intent_id",
              "isExpression": false,
              "asc": true,
              "nulls": "last"
            },
            {
              "expression": "created_at",
              "isExpression": false,
              "asc": true,
              "nulls": "last"
            }
          ],
          "isUnique": false,
          "concurrently": false,
          "method": "btree",
          "with": {}
        }
      },
      "foreignKeys": {
        "payment_attempts_intent_id_payment_intents_id_fk": {
          "name": "payment_attempts_intent_id_payment_intents_id_fk",
          "tableFrom": "payment_attempts",
          "tableTo": "payment_intents",
          "columnsFrom": [
            "intent_id"
          ],
          "columnsTo": [
            "id"
          ],
          "onDelete": "cascade",
          "onUpdate": "no action"
        }
      },
      "compositePrimaryKeys": {},
      "uniqueConstraints": {},
      "policies": {},
      "checkConstraints": {},
      "isRLSEnabled": false
    },
    "public.payment_intents": {
      "name": "payment_intents",
      "schema": "",
      "columns": {
        "id": {
          "name": "id",
          "type": "varchar(36)",
          "primaryKey": true,
          "notNull": true
        },
        "customer_id": {
          "name": "customer_id",
          "type": "varchar(64)",
          "primaryKey": false,
          "notNull": true
        },
        "amount": {
          "name": "amount",
          "type": "bigint",
          "primaryKey": false,
          "notNull": true
        },
        "status": {
          "name": "status",
          "type": "payment_session_status",
          "typeSchema": "public",
          "primaryKey": false,
          "notNull": true,
          "default": "'PENDING'"
        },
        "type": {
          "name": "type",
          "type": "payment_intent_type",
          "typeSchema": "public",
          "primaryKey": false,
          "notNull": true,
          "default": "'ORDER'"
        },
        "expires_at": {
          "name": "expires_at",
          "type": "timestamp with time zone",
          "primaryKey": false,
          "notNull": true
        },
        "metadata": {
          "name": "metadata",
          "type": "jsonb",
          "primaryKey": false,
          "notNull": false
        },
        "refunded_amount": {
          "name": "refunded_amount",
          "type": "bigint",
          "primaryKey": false,
          "notNull": true,
          "default": 0
        },
        "authorized_at": {
          "name": "authorized_at",
          "type": "timestamp with time zone",
          "primaryKey": false,
          "notNull": false
        },
        "captured_at": {
          "name": "captured_at",
          "type": "timestamp with time zone",
          "primaryKey": false,
          "notNull": false
        },
        "created_at": {
          "name": "created_at",
          "type": "timestamp with time zone",
          "primaryKey": false,
          "notNull": true,
          "default": "now()"
        },
        "updated_at": {
          "name": "updated_at",
          "type": "timestamp with time zone",
          "primaryKey": false,
          "notNull": true,
          "default": "now()"
        }
      },
      "indexes": {
        "idx_payment_intents_customer_id": {
          "name": "idx_payment_intents_customer_id",
          "columns": [
            {
              "expression": "customer_id",
              "isExpression": false,
              "asc": true,
              "nulls": "last"
            }
          ],
          "isUnique": false,
          "concurrently": false,
          "method": "btree",
          "with": {}
        },
        "idx_payment_intents_status": {
          "name": "idx_payment_intents_status",
          "columns": [
            {
              "expression": "status",
              "isExpression": false,
              "asc": true,
              "nulls": "last"
            }
          ],
          "isUnique": false,
          "concurrently": false,
          "method": "btree",
          "with": {}
        },
        "idx_payment_intents_type": {
          "name": "idx_payment_intents_type",
          "columns": [
            {
              "expression": "type",
              "isExpression": false,
              "asc": true,
              "nulls": "last"
            }
          ],
          "isUnique": false,
          "concurrently": false,
          "method": "btree",
          "with": {}
        }
      },
      "foreignKeys": {},
      "compositePrimaryKeys": {},
      "uniqueConstraints": {},
      "policies": {},
      "checkConstraints": {},
      "isRLSEnabled": false
    },
    "public.payment_profiles": {
      "name": "payment_profiles",
      "schema": "",
      "columns": {
        "id": {
          "name": "id",
          "type": "varchar(36)",
          "primaryKey": true,
          "notNull": true
        },
        "user_id": {
          "name": "user_id",
          "type": "varchar(64)",
          "primaryKey": false,
          "notNull": true
        },
        "kind": {
          "name": "kind",
          "type": "varchar(16)",
          "primaryKey": false,
          "notNull": true
        },
        "provider": {
          "name": "provider",
          "type": "varchar(16)",
          "primaryKey": false,
          "notNull": true
        },
        "status": {
          "name": "status",
          "type": "payment_profile_status",
          "typeSchema": "public",
          "primaryKey": false,
          "notNull": true,
          "default": "'PENDING'"
        },
        "name": {
          "name": "name",
          "type": "varchar(64)",
          "primaryKey": false,
          "notNull": false
        },
        "created_at": {
          "name": "created_at",
          "type": "timestamp with time zone",
          "primaryKey": false,
          "notNull": true,
          "default": "now()"
        },
        "updated_at": {
          "name": "updated_at",
          "type": "timestamp with time zone",
          "primaryKey": false,
          "notNull": true,
          "default": "now()"
        }
      },
      "indexes": {
        "idx_payment_profiles_user": {
          "name": "idx_payment_profiles_user",
          "columns": [
            {
              "expression": "user_id",
              "isExpression": false,
              "asc": true,
              "nulls": "last"
            }
          ],
          "isUnique": false,
          "concurrently": false,
          "method": "btree",
          "with": {}
        },
        "idx_payment_profiles_kind": {
          "name": "idx_payment_profiles_kind",
          "columns": [
            {
              "expression": "kind",
              "isExpression": false,
              "asc": true,
              "nulls": "last"
            }
          ],
          "isUnique": false,
          "concurrently": false,
          "method": "btree",
          "with": {}
        }
      },
      "foreignKeys": {},
      "compositePrimaryKeys": {},
      "uniqueConstraints": {},
      "policies": {},
      "checkConstraints": {},
      "isRLSEnabled": false
    },
    "public.payment_refunds": {
      "name": "payment_refunds",
      "schema": "",
      "columns": {
        "id": {
          "name": "id",
          "type": "varchar(36)",
          "primaryKey": true,
          "notNull": true
        },
        "intent_id": {
          "name": "intent_id",
          "type": "varchar(36)",
          "primaryKey": false,
          "notNull": true
        },
        "attempt_id": {
          "name": "attempt_id",
          "type": "varchar(36)",
          "primaryKey": false,
          "notNull": true
        },
        "amount": {
          "name": "amount",
          "type": "bigint",
          "primaryKey": false,
          "notNull": true
        },
        "status": {
          "name": "status",
          "type": "refund_status",
          "typeSchema": "public",
          "primaryKey": false,
          "notNull": true
        },
        "reason": {
          "name": "reason",
          "type": "text",
          "primaryKey": false,
          "notNull": false
        },
        "completed_at": {
          "name": "completed_at",
          "type": "timestamp with time zone",
          "primaryKey": false,
          "notNull": false
        },
        "completed_by": {
          "name": "completed_by",
          "type": "varchar(64)",
          "primaryKey": false,
          "notNull": false
        },
        "metadata": {
          "name": "metadata",
          "type": "jsonb",
          "primaryKey": false,
          "notNull": false
        },
        "refund_account_id": {
          "name": "refund_account_id",
          "type": "varchar(36)",
          "primaryKey": false,
          "notNull": false
        },
        "created_at": {
          "name": "created_at",
          "type": "timestamp with time zone",
          "primaryKey": false,
          "notNull": true,
          "default": "now()"
        }
      },
      "indexes": {
        "idx_payment_refunds_intent_id": {
          "name": "idx_payment_refunds_intent_id",
          "columns": [
            {
              "expression": "intent_id",
              "isExpression": false,
              "asc": true,
              "nulls": "last"
            }
          ],
          "isUnique": false,
          "concurrently": false,
          "method": "btree",
          "with": {}
        },
        "idx_payment_refunds_attempt_id": {
          "name": "idx_payment_refunds_attempt_id",
          "columns": [
            {
              "expression": "attempt_id",
              "isExpression": false,
              "asc": true,
              "nulls": "last"
            }
          ],
          "isUnique": false,
          "concurrently": false,
          "method": "btree",
          "with": {}
        },
        "idx_payment_refunds_status": {
          "name": "idx_payment_refunds_status",
          "columns": [
            {
              "expression": "status",
              "isExpression": false,
              "asc": true,
              "nulls": "last"
            }
          ],
          "isUnique": false,
          "concurrently": false,
          "method": "btree",
          "with": {}
        }
      },
      "foreignKeys": {
        "payment_refunds_intent_id_payment_intents_id_fk": {
          "name": "payment_refunds_intent_id_payment_intents_id_fk",
          "tableFrom": "payment_refunds",
          "tableTo": "payment_intents",
          "columnsFrom": [
            "intent_id"
          ],
          "columnsTo": [
            "id"
          ],
          "onDelete": "no action",
          "onUpdate": "no action"
        },
        "payment_refunds_attempt_id_payment_attempts_id_fk": {
          "name": "payment_refunds_attempt_id_payment_attempts_id_fk",
          "tableFrom": "payment_refunds",
          "tableTo": "payment_attempts",
          "columnsFrom": [
            "attempt_id"
          ],
          "columnsTo": [
            "id"
          ],
          "onDelete": "no action",
          "onUpdate": "no action"
        },
        "payment_refunds_refund_account_id_user_refund_accounts_id_fk": {
          "name": "payment_refunds_refund_account_id_user_refund_accounts_id_fk",
          "tableFrom": "payment_refunds",
          "tableTo": "user_refund_accounts",
          "columnsFrom": [
            "refund_account_id"
          ],
          "columnsTo": [
            "id"
          ],
          "onDelete": "no action",
          "onUpdate": "no action"
        }
      },
      "compositePrimaryKeys": {},
      "uniqueConstraints": {},
      "policies": {},
      "checkConstraints": {},
      "isRLSEnabled": false
    },
    "public.point_event_details": {
      "name": "point_event_details",
      "schema": "",
      "columns": {
        "id": {
          "name": "id",
          "type": "serial",
          "primaryKey": true,
          "notNull": true
        },
        "point_event_id": {
          "name": "point_event_id",
          "type": "integer",
          "primaryKey": false,
          "notNull": true
        },
        "partner_id": {
          "name": "partner_id",
          "type": "integer",
          "primaryKey": false,
          "notNull": true
        },
        "event_type": {
          "name": "event_type",
          "type": "point_action",
          "typeSchema": "public",
          "primaryKey": false,
          "notNull": true
        },
        "amount": {
          "name": "amount",
          "type": "integer",
          "primaryKey": false,
          "notNull": true
        },
        "earned_event_detail_id": {
          "name": "earned_event_detail_id",
          "type": "integer",
          "primaryKey": false,
          "notNull": false
        },
        "original_event_detail_id": {
          "name": "original_event_detail_id",
          "type": "integer",
          "primaryKey": false,
          "notNull": false
        },
        "created_at": {
          "name": "created_at",
          "type": "timestamp with time zone",
          "primaryKey": false,
          "notNull": true,
          "default": "now()"
        }
      },
      "indexes": {
        "idx_point_event_details_event": {
          "name": "idx_point_event_details_event",
          "columns": [
            {
              "expression": "point_event_id",
              "isExpression": false,
              "asc": true,
              "nulls": "last"
            }
          ],
          "isUnique": false,
          "concurrently": false,
          "method": "btree",
          "with": {}
        },
        "idx_point_event_details_partner": {
          "name": "idx_point_event_details_partner",
          "columns": [
            {
              "expression": "partner_id",
              "isExpression": false,
              "asc": true,
              "nulls": "last"
            }
          ],
          "isUnique": false,
          "concurrently": false,
          "method": "btree",
          "with": {}
        },
        "idx_point_event_details_earned": {
          "name": "idx_point_event_details_earned",
          "columns": [
            {
              "expression": "earned_event_detail_id",
              "isExpression": false,
              "asc": true,
              "nulls": "last"
            }
          ],
          "isUnique": false,
          "concurrently": false,
          "method": "btree",
          "with": {}
        },
        "idx_point_event_details_original": {
          "name": "idx_point_event_details_original",
          "columns": [
            {
              "expression": "original_event_detail_id",
              "isExpression": false,
              "asc": true,
              "nulls": "last"
            }
          ],
          "isUnique": false,
          "concurrently": false,
          "method": "btree",
          "with": {}
        }
      },
      "foreignKeys": {
        "point_event_details_point_event_id_point_events_id_fk": {
          "name": "point_event_details_point_event_id_point_events_id_fk",
          "tableFrom": "point_event_details",
          "tableTo": "point_events",
          "columnsFrom": [
            "point_event_id"
          ],
          "columnsTo": [
            "id"
          ],
          "onDelete": "no action",
          "onUpdate": "no action"
        },
        "point_event_details_earned_event_detail_id_point_event_details_id_fk": {
          "name": "point_event_details_earned_event_detail_id_point_event_details_id_fk",
          "tableFrom": "point_event_details",
          "tableTo": "point_event_details",
          "columnsFrom": [
            "earned_event_detail_id"
          ],
          "columnsTo": [
            "id"
          ],
          "onDelete": "no action",
          "onUpdate": "no action"
        },
        "point_event_details_original_event_detail_id_point_event_details_id_fk": {
          "name": "point_event_details_original_event_detail_id_point_event_details_id_fk",
          "tableFrom": "point_event_details",
          "tableTo": "point_event_details",
          "columnsFrom": [
            "original_event_detail_id"
          ],
          "columnsTo": [
            "id"
          ],
          "onDelete": "no action",
          "onUpdate": "no action"
        }
      },
      "compositePrimaryKeys": {},
      "uniqueConstraints": {},
      "policies": {},
      "checkConstraints": {},
      "isRLSEnabled": false
    },
    "public.point_events": {
      "name": "point_events",
      "schema": "",
      "columns": {
        "id": {
          "name": "id",
          "type": "serial",
          "primaryKey": true,
          "notNull": true
        },
        "partner_id": {
          "name": "partner_id",
          "type": "integer",
          "primaryKey": false,
          "notNull": true
        },
        "event_type": {
          "name": "event_type",
          "type": "point_action",
          "typeSchema": "public",
          "primaryKey": false,
          "notNull": true
        },
        "amount": {
          "name": "amount",
          "type": "integer",
          "primaryKey": false,
          "notNull": true
        },
        "expires_at": {
          "name": "expires_at",
          "type": "timestamp with time zone",
          "primaryKey": false,
          "notNull": false
        },
        "withdrawal_available_at": {
          "name": "withdrawal_available_at",
          "type": "timestamp with time zone",
          "primaryKey": false,
          "notNull": false
        },
        "reason": {
          "name": "reason",
          "type": "text",
          "primaryKey": false,
          "notNull": false
        },
        "memo": {
          "name": "memo",
          "type": "text",
          "primaryKey": false,
          "notNull": false
        },
        "order_id": {
          "name": "order_id",
          "type": "varchar(100)",
          "primaryKey": false,
          "notNull": false
        },
        "original_event_id": {
          "name": "original_event_id",
          "type": "integer",
          "primaryKey": false,
          "notNull": false
        },
        "created_at": {
          "name": "created_at",
          "type": "timestamp with time zone",
          "primaryKey": false,
          "notNull": true,
          "default": "now()"
        }
      },
      "indexes": {
        "idx_point_events_partner": {
          "name": "idx_point_events_partner",
          "columns": [
            {
              "expression": "partner_id",
              "isExpression": false,
              "asc": true,
              "nulls": "last"
            }
          ],
          "isUnique": false,
          "concurrently": false,
          "method": "btree",
          "with": {}
        },
        "idx_point_events_type": {
          "name": "idx_point_events_type",
          "columns": [
            {
              "expression": "event_type",
              "isExpression": false,
              "asc": true,
              "nulls": "last"
            }
          ],
          "isUnique": false,
          "concurrently": false,
          "method": "btree",
          "with": {}
        },
        "idx_point_events_expires": {
          "name": "idx_point_events_expires",
          "columns": [
            {
              "expression": "expires_at",
              "isExpression": false,
              "asc": true,
              "nulls": "last"
            }
          ],
          "isUnique": false,
          "concurrently": false,
          "method": "btree",
          "with": {}
        },
        "idx_point_events_original": {
          "name": "idx_point_events_original",
          "columns": [
            {
              "expression": "original_event_id",
              "isExpression": false,
              "asc": true,
              "nulls": "last"
            }
          ],
          "isUnique": false,
          "concurrently": false,
          "method": "btree",
          "with": {}
        }
      },
      "foreignKeys": {
        "point_events_original_event_id_point_events_id_fk": {
          "name": "point_events_original_event_id_point_events_id_fk",
          "tableFrom": "point_events",
          "tableTo": "point_events",
          "columnsFrom": [
            "original_event_id"
          ],
          "columnsTo": [
            "id"
          ],
          "onDelete": "no action",
          "onUpdate": "no action"
        }
      },
      "compositePrimaryKeys": {},
      "uniqueConstraints": {},
      "policies": {},
      "checkConstraints": {},
      "isRLSEnabled": false
    },
    "public.referral_rewards": {
      "name": "referral_rewards",
      "schema": "",
      "columns": {
        "mall_id": {
          "name": "mall_id",
          "type": "varchar(36)",
          "primaryKey": false,
          "notNull": true
        },
        "member_id": {
          "name": "member_id",
          "type": "varchar(36)",
          "primaryKey": false,
          "notNull": true
        },
        "request_id": {
          "name": "request_id",
          "type": "integer",
          "primaryKey": false,
          "notNull": true
        },
        "rewarded_at": {
          "name": "rewarded_at",
          "type": "timestamp with time zone",
          "primaryKey": false,
          "notNull": true,
          "default": "now()"
        }
      },
      "indexes": {
        "idx_referral_rewards_member": {
          "name": "idx_referral_rewards_member",
          "columns": [
            {
              "expression": "member_id",
              "isExpression": false,
              "asc": true,
              "nulls": "last"
            }
          ],
          "isUnique": false,
          "concurrently": false,
          "method": "btree",
          "with": {}
        },
        "idx_referral_rewards_mall": {
          "name": "idx_referral_rewards_mall",
          "columns": [
            {
              "expression": "mall_id",
              "isExpression": false,
              "asc": true,
              "nulls": "last"
            }
          ],
          "isUnique": false,
          "concurrently": false,
          "method": "btree",
          "with": {}
        },
        "idx_referral_rewards_unique": {
          "name": "idx_referral_rewards_unique",
          "columns": [
            {
              "expression": "mall_id",
              "isExpression": false,
              "asc": true,
              "nulls": "last"
            },
            {
              "expression": "member_id",
              "isExpression": false,
              "asc": true,
              "nulls": "last"
            }
          ],
          "isUnique": true,
          "concurrently": false,
          "method": "btree",
          "with": {}
        }
      },
      "foreignKeys": {},
      "compositePrimaryKeys": {},
      "uniqueConstraints": {},
      "policies": {},
      "checkConstraints": {},
      "isRLSEnabled": false
    },
    "public.referrals": {
      "name": "referrals",
      "schema": "",
      "columns": {
        "mall_id": {
          "name": "mall_id",
          "type": "varchar(36)",
          "primaryKey": false,
          "notNull": true
        },
        "member_id": {
          "name": "member_id",
          "type": "varchar(36)",
          "primaryKey": false,
          "notNull": true
        },
        "partner_id": {
          "name": "partner_id",
          "type": "integer",
          "primaryKey": false,
          "notNull": true
        },
        "created_at": {
          "name": "created_at",
          "type": "timestamp with time zone",
          "primaryKey": false,
          "notNull": true,
          "default": "now()"
        }
      },
      "indexes": {
        "idx_referrals_member": {
          "name": "idx_referrals_member",
          "columns": [
            {
              "expression": "member_id",
              "isExpression": false,
              "asc": true,
              "nulls": "last"
            }
          ],
          "isUnique": false,
          "concurrently": false,
          "method": "btree",
          "with": {}
        },
        "idx_referrals_partner": {
          "name": "idx_referrals_partner",
          "columns": [
            {
              "expression": "partner_id",
              "isExpression": false,
              "asc": true,
              "nulls": "last"
            }
          ],
          "isUnique": false,
          "concurrently": false,
          "method": "btree",
          "with": {}
        },
        "idx_referrals_mall": {
          "name": "idx_referrals_mall",
          "columns": [
            {
              "expression": "mall_id",
              "isExpression": false,
              "asc": true,
              "nulls": "last"
            }
          ],
          "isUnique": false,
          "concurrently": false,
          "method": "btree",
          "with": {}
        }
      },
      "foreignKeys": {
        "referrals_partner_id_partners_id_fk": {
          "name": "referrals_partner_id_partners_id_fk",
          "tableFrom": "referrals",
          "tableTo": "partners",
          "columnsFrom": [
            "partner_id"
          ],
          "columnsTo": [
            "id"
          ],
          "onDelete": "no action",
          "onUpdate": "no action"
        }
      },
      "compositePrimaryKeys": {},
      "uniqueConstraints": {},
      "policies": {},
      "checkConstraints": {},
      "isRLSEnabled": false
    },
    "public.user_refund_accounts": {
      "name": "user_refund_accounts",
      "schema": "",
      "columns": {
        "id": {
          "name": "id",
          "type": "varchar(36)",
          "primaryKey": true,
          "notNull": true
        },
        "user_id": {
          "name": "user_id",
          "type": "varchar(64)",
          "primaryKey": false,
          "notNull": true
        },
        "bank_code": {
          "name": "bank_code",
          "type": "varchar(32)",
          "primaryKey": false,
          "notNull": true
        },
        "bank_name": {
          "name": "bank_name",
          "type": "varchar(64)",
          "primaryKey": false,
          "notNull": true
        },
        "account_number": {
          "name": "account_number",
          "type": "varchar(64)",
          "primaryKey": false,
          "notNull": true
        },
        "account_holder_name": {
          "name": "account_holder_name",
          "type": "varchar(128)",
          "primaryKey": false,
          "notNull": true
        },
        "is_default": {
          "name": "is_default",
          "type": "boolean",
          "primaryKey": false,
          "notNull": true,
          "default": false
        },
        "created_at": {
          "name": "created_at",
          "type": "timestamp with time zone",
          "primaryKey": false,
          "notNull": true,
          "default": "now()"
        },
        "updated_at": {
          "name": "updated_at",
          "type": "timestamp with time zone",
          "primaryKey": false,
          "notNull": true,
          "default": "now()"
        }
      },
      "indexes": {
        "idx_user_default_refund_account": {
          "name": "idx_user_default_refund_account",
          "columns": [
            {
              "expression": "user_id",
              "isExpression": false,
              "asc": true,
              "nulls": "last"
            }
          ],
          "isUnique": true,
          "where": "\"user_refund_accounts\".\"is_default\" = true",
          "concurrently": false,
          "method": "btree",
          "with": {}
        }
      },
      "foreignKeys": {},
      "compositePrimaryKeys": {},
      "uniqueConstraints": {},
      "policies": {},
      "checkConstraints": {},
      "isRLSEnabled": false
    }
  },
  "enums": {
    "public.bnpl_account_status": {
      "name": "bnpl_account_status",
      "schema": "public",
      "values": [
        "ACTIVE",
        "SUSPENDED",
        "OVERDUE"
      ]
    },
    "public.payment_intent_type": {
      "name": "payment_intent_type",
      "schema": "public",
      "values": [
        "ORDER",
        "BNPL_CAPTURE",
        "MEMBERSHIP_FEE"
      ]
    },
    "public.payment_profile_status": {
      "name": "payment_profile_status",
      "schema": "public",
      "values": [
        "PENDING",
        "ACTIVE",
        "INACTIVE"
      ]
    },
    "public.payment_provider": {
      "name": "payment_provider",
      "schema": "public",
      "values": [
        "TOSS",
        "KAKAOPAY",
        "HMS_CARD",
        "HMS_BNPL",
        "POINTS"
      ]
    },
    "public.payment_purpose": {
      "name": "payment_purpose",
      "schema": "public",
      "values": [
        "SUBSCRIPTION",
        "PURCHASE",
        "BOTH"
      ]
    },
    "public.payment_session_status": {
      "name": "payment_session_status",
      "schema": "public",
      "values": [
        "PENDING",
        "AUTHORIZED",
        "CAPTURED",
        "FAILED",
        "CANCELLED",
        "PARTIALLY_REFUNDED",
        "REFUNDED"
      ]
    },
    "public.point_action": {
      "name": "point_action",
      "schema": "public",
      "values": [
        "EARN",
        "EARN_CANCEL",
        "REDEEM",
        "REDEEM_CANCEL"
      ]
    },
    "public.refund_status": {
      "name": "refund_status",
      "schema": "public",
      "values": [
        "REQUESTED",
        "APPROVED",
        "COMPLETED",
        "CANCELLED",
        "FAILED"
      ]
    },
    "public.transaction_status": {
      "name": "transaction_status",
      "schema": "public",
      "values": [
        "AUTHORIZED",
        "CAPTURED",
        "FAILED",
        "CANCELLED"
      ]
    }
  },
  "schemas": {},
  "sequences": {},
  "roles": {},
  "policies": {},
  "views": {},
  "_meta": {
    "columns": {},
    "schemas": {},
    "tables": {}
  }
}